nb_cli_plugin_rplugin/__init__.py
nb_cli_plugin_rplugin/cli.py
nb_cli_plugin_rplugin/exception.py
nb_cli_plugin_rplugin/handler.py
nb_cli_plugin_rplugin/installer.py
nb_cli_plugin_rplugin/locale/zh_CN/LC_MESSAGES/nb-cli-plugin-rplugin.mo
nb_cli_plugin_rplugin/locale/zh_CN/LC_MESSAGES/nb-cli-plugin-rplugin.po
nb_cli_plugin_rplugin/manager.py
nb_cli_plugin_rplugin/meta.py
nb_cli_plugin_rplugin/prompt.py
nb_cli_plugin_rplugin/py.typed
nb_cli_plugin_rplugin-0.1.0.dist-info/entry_points.txt
nb_cli_plugin_rplugin-0.1.0.dist-info/WHEEL
nb_cli_plugin_rplugin-0.1.0.dist-info/METADATA
nb_cli_plugin_rplugin-0.1.0.dist-info/licenses/LICENSE
nb_cli_plugin_rplugin-0.1.0.dist-info/RECORD
