Metadata-Version: 2.1
Name: nb-cli-plugin-rplugin
Version: 0.1.0
Summary: nb-cli 富文本插件管理
License: MIT
Keywords: bot,cli,nonebot,nb-cli
Author-email: MingxuanGame <MingxuanGame@outlook.com>
Requires-Python: >=3.8
Classifier: Development Status :: 5 - Production/Stable
Classifier: Framework :: Robot Framework
Classifier: Framework :: Robot Framework :: Library
Classifier: License :: OSI Approved :: MIT License
Classifier: Operating System :: OS Independent
Classifier: Programming Language :: Python :: 3
Requires-Dist: nb-cli>=1.0.0
Requires-Dist: rich>=13.0.1
